pytest_manifest.py
pytest_manifest-1.0.2.dist-info/METADATA
pytest_manifest-1.0.2.dist-info/WHEEL
pytest_manifest-1.0.2.dist-info/entry_points.txt
pytest_manifest-1.0.2.dist-info/top_level.txt
pytest_manifest-1.0.2.dist-info/RECORD
