Metadata-Version: 2.1
Name: pytest-manifest
Version: 1.0.2
Summary: PyTest plugin for recording and asserting against a manifest file
Author-email: Conrad Bzura <conradbzura@gmail.com>
License: MIT License
Classifier: Framework :: Pytest
Classifier: Programming Language :: Python :: 3.8
Classifier: Programming Language :: Python :: 3.9
Classifier: Programming Language :: Python :: 3.10
Classifier: Programming Language :: Python :: 3.11
Classifier: Programming Language :: Python :: 3.12
Classifier: Programming Language :: Python :: 3.13
Requires-Python: >=3.8
Requires-Dist: pytest
Requires-Dist: pyyaml
